{
	"authHost": "http://localhost",
	"authEndpoint": "/broadcasting/auth",
	"clients": [
		{
			"appId": "945c34e7b66b27a8",
			"key": "95b6b704b38794037e196f8748433a15"
		}
	],
	"database": "redis",
	"databaseConfig": {
		"redis": {},
		"sqlite": {
			"databasePath": "/database/laravel-echo-server.sqlite"
		}
	},
	"devMode": true,
	"host": null,
	"port": "6001",
	"protocol": "http",
	"socketio": {},
	"secureOptions": 67108864,
	"sslCertPath": "",
	"sslKeyPath": "",
	"sslCertChainPath": "",
	"sslPassphrase": "",
	"subscribers": {
		"http": true,
		"redis": true
	},
	"apiOriginAllow": {
		"allowCors": true,
		"allowOrigin": "http://localhost:80/api/",
		"allowMethods": "get",
		"allowHeaders": "get"
	}
}